{
    "description": "CMake is an open-source, cross-platform family of tools designed to build, test and package software",
    "version": "3.17.1",
    "url": [
        "https://github.com/Kitware/CMake/releases/download/v3.17.2/cmake-3.17.2-win32-x86.zip",
        "https://cmake.org/files/v3.17/cmake-3.17.2-win32-x86.zip"
    ],
    "url.hash": "SHA256:66a68a1032ad1853bcff01778ae190cd461d174d6a689e1c646e3e9886f01e0a",
    "url64": [
        "https://github.com/Kitware/CMake/releases/download/v3.17.2/cmake-3.17.2-win64-x64.zip",
        "https://cmake.org/files/v3.17/cmake-3.17.2-win64-x64.zip"
    ],
    "url64.hash": "SHA256:cf82b1eb20b6fbe583487656fcd496490ffccdfbcbba0f26e19f1c9c63b0b041",
    "extension": "zip",
    "links": [
        "bin\\cmake.exe",
        "bin\\cmake-gui.exe",
        "bin\\cmcldeps.exe",
        "bin\\cpack.exe",
        "bin\\ctest.exe"
    ]
}